pyrbd/__init__.py
pyrbd/block.py
pyrbd/config.py
pyrbd/diagram.py
pyrbd/py.typed
pyrbd/templates.py
pyrbd/templates/block.tex.jinja
pyrbd/templates/diagram.tex.jinja
pyrbd/templates/group.tex.jinja
pyrbd/templates/series.tex.jinja
pyrbd-0.4.2.dist-info/METADATA
pyrbd-0.4.2.dist-info/WHEEL
pyrbd-0.4.2.dist-info/licenses/LICENSE
pyrbd-0.4.2.dist-info/RECORD
