Metadata-Version: 2.4
Name: pyrbd
Version: 0.4.2
Summary: Package for creating simple reliability block diagrams (RBDs) using LaTeX and TikZ.
Project-URL: Repository, https://github.com/hghugdal/pyrbd
Project-URL: Issues, https://github.com/hghugdal/pyrbd/issues
Project-URL: Documentation, https://hghugdal.github.io/pyrbd
Author-email: hghugdal <hghugdal@gmail.com>
License-Expression: MIT
License-File: LICENSE
Classifier: Development Status :: 4 - Beta
Classifier: Programming Language :: Python :: 3
Requires-Python: >=3.10
Requires-Dist: jinja2>=3.1.6
Requires-Dist: pymupdf>=1.26.3
